adb_enhanced-2.8.0.dist-info/licenses/LICENSE
adbe/__init__.py
adbe/abe.jar
adbe/adb_enhanced.py
adbe/adb_helper.py
adbe/apksigner.jar
adbe/asyncio_helper.py
adbe/main.py
adbe/output_helper.py
adbe/version.txt
adb_enhanced-2.8.0.dist-info/METADATA
adb_enhanced-2.8.0.dist-info/WHEEL
adb_enhanced-2.8.0.dist-info/entry_points.txt
adb_enhanced-2.8.0.dist-info/top_level.txt
adb_enhanced-2.8.0.dist-info/RECORD
