Metadata-Version: 2.4
Name: adb-enhanced
Version: 2.8.0
Summary: ADB-Enhanced is a Swiss army knife for Android testing and development
Author-email: Ashish Bhatia <ashishb@ashishb.net>
License-Expression: Apache-2.0
Keywords: Android ADB developer
Classifier: Intended Audience :: Developers
Classifier: Operating System :: Android
Requires-Python: >=3.10
License-File: LICENSE
Requires-Dist: docopt==0.6.2
Requires-Dist: psutil==7.2.1
Dynamic: license-file
